{
  "Top": "DTJSCC",
  "RtlTop": "DTJSCC",
  "RtlPrefix": "",
  "RtlSubPrefix": "DTJSCC_",
  "SourceLanguage": "cpp",
  "HostMachineBits": "64",
  "FunctionProtocol": "ap_ctrl_hs",
  "ResetStyle": "control",
  "Target": {
    "Family": "versal",
    "Device": "xcvp1802",
    "Package": "-lsvc4072",
    "Speed": "-1LHP-i-L",
    "Triple": "fpga64-xilinx-none"
  },
  "Args": {
    "img_in": {
      "index": "0",
      "direction": "unused",
      "srcType": "float*",
      "srcSize": "32",
      "hwRefs": [
        {
          "type": "port",
          "interface": "img_in_address0",
          "name": "img_in_address0",
          "usage": "address",
          "direction": "out"
        },
        {
          "type": "port",
          "interface": "img_in_ce0",
          "name": "img_in_ce0",
          "usage": "control",
          "direction": "out"
        },
        {
          "type": "port",
          "interface": "img_in_we0",
          "name": "img_in_we0",
          "usage": "control",
          "direction": "out"
        },
        {
          "type": "port",
          "interface": "img_in_d0",
          "name": "img_in_d0",
          "usage": "data",
          "direction": "out"
        },
        {
          "type": "port",
          "interface": "img_in_q0",
          "name": "img_in_q0",
          "usage": "data",
          "direction": "in"
        },
        {
          "type": "port",
          "interface": "img_in_address1",
          "name": "img_in_address1",
          "usage": "address",
          "direction": "out"
        },
        {
          "type": "port",
          "interface": "img_in_ce1",
          "name": "img_in_ce1",
          "usage": "control",
          "direction": "out"
        },
        {
          "type": "port",
          "interface": "img_in_we1",
          "name": "img_in_we1",
          "usage": "control",
          "direction": "out"
        },
        {
          "type": "port",
          "interface": "img_in_d1",
          "name": "img_in_d1",
          "usage": "data",
          "direction": "out"
        },
        {
          "type": "port",
          "interface": "img_in_q1",
          "name": "img_in_q1",
          "usage": "data",
          "direction": "in"
        }
      ]
    },
    "mm": {
      "index": "1",
      "direction": "unused",
      "srcType": "float*",
      "srcSize": "32",
      "hwRefs": [
        {
          "type": "port",
          "interface": "mm_address0",
          "name": "mm_address0",
          "usage": "address",
          "direction": "out"
        },
        {
          "type": "port",
          "interface": "mm_ce0",
          "name": "mm_ce0",
          "usage": "control",
          "direction": "out"
        },
        {
          "type": "port",
          "interface": "mm_we0",
          "name": "mm_we0",
          "usage": "control",
          "direction": "out"
        },
        {
          "type": "port",
          "interface": "mm_d0",
          "name": "mm_d0",
          "usage": "data",
          "direction": "out"
        },
        {
          "type": "port",
          "interface": "mm_q0",
          "name": "mm_q0",
          "usage": "data",
          "direction": "in"
        },
        {
          "type": "port",
          "interface": "mm_address1",
          "name": "mm_address1",
          "usage": "address",
          "direction": "out"
        },
        {
          "type": "port",
          "interface": "mm_ce1",
          "name": "mm_ce1",
          "usage": "control",
          "direction": "out"
        },
        {
          "type": "port",
          "interface": "mm_we1",
          "name": "mm_we1",
          "usage": "control",
          "direction": "out"
        },
        {
          "type": "port",
          "interface": "mm_d1",
          "name": "mm_d1",
          "usage": "data",
          "direction": "out"
        },
        {
          "type": "port",
          "interface": "mm_q1",
          "name": "mm_q1",
          "usage": "data",
          "direction": "in"
        }
      ]
    }
  },
  "HlsSolution": {
    "FlowTarget": "vivado",
    "DirectiveTcl": [
      "set_directive_top DTJSCC -name DTJSCC",
      "set_directive_top DTJSCC -name DTJSCC"
    ],
    "ProfileOption": "0",
    "ProfileType": "none",
    "KernelName": "DTJSCC"
  },
  "ClockInfo": {
    "ClockName": "ap_clk",
    "ClockPeriod": "10",
    "Uncertainty": "2.7",
    "IsCombinational": "1",
    "II": "1",
    "Latency": "0"
  },
  "Xdc": {
    
  },
  "Ipx": {
    "Vendor": "xilinx.com",
    "Library": "hls",
    "Name": "DTJSCC",
    "Version": "1.0",
    "DisplayName": "Dtjscc",
    "Revision": "2113963624",
    "Description": "An IP generated by Vitis HLS",
    "Taxonomy": "\/VITIS_HLS_IP",
    "AutoFamilySupport": "",
    "ZipFile": "xilinx_com_hls_DTJSCC_1_0.zip"
  },
  "Files": {
    "CSource": [
      "..\/..\/DDR_write.cpp",
      "..\/..\/DTJSCC.cpp",
      "..\/..\/Function.cpp"
    ],
    "Vhdl": ["impl\/vhdl\/DTJSCC.vhd"],
    "Verilog": ["impl\/verilog\/DTJSCC.v"],
    "IpMisc": ["impl\/misc\/logo.png"],
    "CsynthXml": "syn\/report\/csynth.xml",
    "DebugDir": ".debug",
    "KernelXml": ".autopilot\/db\/kernel.internal.xml",
    "Xo": "",
    "XoHlsDir": "",
    "ProtoInst": [".debug\/DTJSCC.protoinst"]
  },
  "SubcoreInfo": {
    "HasXpmMemory": false,
    "HasClockedDsp": false,
    "Ip": []
  },
  "Interfaces": {
    "ap_ctrl": {
      "type": "ap_ctrl",
      "busTypeName": "acc_handshake",
      "mode": "slave",
      "portMap": {
        "ap_start": "start",
        "ap_done": "done",
        "ap_idle": "idle",
        "ap_ready": "ready"
      },
      "ports": [
        "ap_done",
        "ap_idle",
        "ap_ready",
        "ap_start"
      ]
    },
    "img_in_address0": {
      "type": "data",
      "busTypeName": "data",
      "protocol": "ap_memory",
      "mode": "master",
      "dataWidth": "10",
      "portMap": {"img_in_address0": "DATA"},
      "ports": ["img_in_address0"],
      "constraints": [{
          "constraint_type": "pragma interface",
          "mode": "ap_memory",
          "register_option": "0",
          "argName": "img_in"
        }]
    },
    "img_in_d0": {
      "type": "data",
      "busTypeName": "data",
      "protocol": "ap_memory",
      "mode": "master",
      "dataWidth": "32",
      "portMap": {"img_in_d0": "DATA"},
      "ports": ["img_in_d0"],
      "constraints": [{
          "constraint_type": "pragma interface",
          "mode": "ap_memory",
          "register_option": "0",
          "argName": "img_in"
        }]
    },
    "img_in_q0": {
      "type": "data",
      "busTypeName": "data",
      "protocol": "ap_memory",
      "mode": "slave",
      "dataWidth": "32",
      "portMap": {"img_in_q0": "DATA"},
      "ports": ["img_in_q0"],
      "constraints": [{
          "constraint_type": "pragma interface",
          "mode": "ap_memory",
          "register_option": "0",
          "argName": "img_in"
        }]
    },
    "img_in_address1": {
      "type": "data",
      "busTypeName": "data",
      "protocol": "ap_memory",
      "mode": "master",
      "dataWidth": "10",
      "portMap": {"img_in_address1": "DATA"},
      "ports": ["img_in_address1"],
      "constraints": [{
          "constraint_type": "pragma interface",
          "mode": "ap_memory",
          "register_option": "0",
          "argName": "img_in"
        }]
    },
    "img_in_d1": {
      "type": "data",
      "busTypeName": "data",
      "protocol": "ap_memory",
      "mode": "master",
      "dataWidth": "32",
      "portMap": {"img_in_d1": "DATA"},
      "ports": ["img_in_d1"],
      "constraints": [{
          "constraint_type": "pragma interface",
          "mode": "ap_memory",
          "register_option": "0",
          "argName": "img_in"
        }]
    },
    "img_in_q1": {
      "type": "data",
      "busTypeName": "data",
      "protocol": "ap_memory",
      "mode": "slave",
      "dataWidth": "32",
      "portMap": {"img_in_q1": "DATA"},
      "ports": ["img_in_q1"],
      "constraints": [{
          "constraint_type": "pragma interface",
          "mode": "ap_memory",
          "register_option": "0",
          "argName": "img_in"
        }]
    },
    "mm_address0": {
      "type": "data",
      "busTypeName": "data",
      "protocol": "ap_memory",
      "mode": "master",
      "dataWidth": "4",
      "portMap": {"mm_address0": "DATA"},
      "ports": ["mm_address0"],
      "constraints": [{
          "constraint_type": "pragma interface",
          "mode": "ap_memory",
          "register_option": "0",
          "argName": "mm"
        }]
    },
    "mm_d0": {
      "type": "data",
      "busTypeName": "data",
      "protocol": "ap_memory",
      "mode": "master",
      "dataWidth": "32",
      "portMap": {"mm_d0": "DATA"},
      "ports": ["mm_d0"],
      "constraints": [{
          "constraint_type": "pragma interface",
          "mode": "ap_memory",
          "register_option": "0",
          "argName": "mm"
        }]
    },
    "mm_q0": {
      "type": "data",
      "busTypeName": "data",
      "protocol": "ap_memory",
      "mode": "slave",
      "dataWidth": "32",
      "portMap": {"mm_q0": "DATA"},
      "ports": ["mm_q0"],
      "constraints": [{
          "constraint_type": "pragma interface",
          "mode": "ap_memory",
          "register_option": "0",
          "argName": "mm"
        }]
    },
    "mm_address1": {
      "type": "data",
      "busTypeName": "data",
      "protocol": "ap_memory",
      "mode": "master",
      "dataWidth": "4",
      "portMap": {"mm_address1": "DATA"},
      "ports": ["mm_address1"],
      "constraints": [{
          "constraint_type": "pragma interface",
          "mode": "ap_memory",
          "register_option": "0",
          "argName": "mm"
        }]
    },
    "mm_d1": {
      "type": "data",
      "busTypeName": "data",
      "protocol": "ap_memory",
      "mode": "master",
      "dataWidth": "32",
      "portMap": {"mm_d1": "DATA"},
      "ports": ["mm_d1"],
      "constraints": [{
          "constraint_type": "pragma interface",
          "mode": "ap_memory",
          "register_option": "0",
          "argName": "mm"
        }]
    },
    "mm_q1": {
      "type": "data",
      "busTypeName": "data",
      "protocol": "ap_memory",
      "mode": "slave",
      "dataWidth": "32",
      "portMap": {"mm_q1": "DATA"},
      "ports": ["mm_q1"],
      "constraints": [{
          "constraint_type": "pragma interface",
          "mode": "ap_memory",
          "register_option": "0",
          "argName": "mm"
        }]
    }
  },
  "RtlPorts": {
    "ap_start": {
      "dir": "in",
      "width": "1"
    },
    "ap_done": {
      "dir": "out",
      "width": "1"
    },
    "ap_idle": {
      "dir": "out",
      "width": "1"
    },
    "ap_ready": {
      "dir": "out",
      "width": "1"
    },
    "img_in_address0": {
      "dir": "out",
      "width": "10"
    },
    "img_in_ce0": {
      "dir": "out",
      "width": "1"
    },
    "img_in_we0": {
      "dir": "out",
      "width": "1"
    },
    "img_in_d0": {
      "dir": "out",
      "width": "32"
    },
    "img_in_q0": {
      "dir": "in",
      "width": "32"
    },
    "img_in_address1": {
      "dir": "out",
      "width": "10"
    },
    "img_in_ce1": {
      "dir": "out",
      "width": "1"
    },
    "img_in_we1": {
      "dir": "out",
      "width": "1"
    },
    "img_in_d1": {
      "dir": "out",
      "width": "32"
    },
    "img_in_q1": {
      "dir": "in",
      "width": "32"
    },
    "mm_address0": {
      "dir": "out",
      "width": "4"
    },
    "mm_ce0": {
      "dir": "out",
      "width": "1"
    },
    "mm_we0": {
      "dir": "out",
      "width": "1"
    },
    "mm_d0": {
      "dir": "out",
      "width": "32"
    },
    "mm_q0": {
      "dir": "in",
      "width": "32"
    },
    "mm_address1": {
      "dir": "out",
      "width": "4"
    },
    "mm_ce1": {
      "dir": "out",
      "width": "1"
    },
    "mm_we1": {
      "dir": "out",
      "width": "1"
    },
    "mm_d1": {
      "dir": "out",
      "width": "32"
    },
    "mm_q1": {
      "dir": "in",
      "width": "32"
    }
  },
  "ModuleInfo": {
    "Hierarchy": {"ModuleName": "DTJSCC"},
    "Info": {"DTJSCC": {
        "FunctionProtocol": "ap_ctrl_hs",
        "isTaskLevelControl": "0",
        "isPipelined": "0",
        "isCombinational": "1",
        "isOneStateSeq": "0"
      }},
    "Metrics": {"DTJSCC": {
        "Latency": {
          "LatencyBest": "0",
          "LatencyAvg": "0",
          "LatencyWorst": "0",
          "PipelineII": "1",
          "PipelineDepth": "",
          "PipelineType": "no"
        },
        "Timing": {
          "Target": "10.00",
          "Uncertainty": "2.70",
          "Estimate": "0.000"
        },
        "Area": {
          "BRAM_18K": "0",
          "AVAIL_BRAM": "9882",
          "UTIL_BRAM": "0",
          "DSP": "0",
          "AVAIL_DSP": "14352",
          "UTIL_DSP": "0",
          "FF": "0",
          "AVAIL_FF": "6721792",
          "UTIL_FF": "0",
          "LUT": "0",
          "AVAIL_LUT": "3360896",
          "UTIL_LUT": "0",
          "URAM": "0",
          "AVAIL_URAM": "2549",
          "UTIL_URAM": "0"
        }
      }}
  },
  "GenerateBdFiles": "0",
  "GenData": {
    "DataVersion": "0.2",
    "Time": "2025-02-20 17:04:57 +0800",
    "ToolName": "vitis_hls",
    "ToolVersion": "2023.2"
  }
}
